gradient_adk/__init__.py
gradient_adk/decorator.py
gradient_adk/logging.py
gradient_adk/tracing.py
gradient_adk/cli/__init__.py
gradient_adk/cli/cli.py
gradient_adk/cli/agent/direct_launch_service.py
gradient_adk/cli/agent/env_utils.py
gradient_adk/cli/agent/evaluation_service.py
gradient_adk/cli/agent/launch_service.py
gradient_adk/cli/agent/traces_service.py
gradient_adk/cli/agent/deployment/deploy_service.py
gradient_adk/cli/agent/deployment/validation.py
gradient_adk/cli/agent/deployment/utils/__init__.py
gradient_adk/cli/agent/deployment/utils/s3_utils.py
gradient_adk/cli/agent/deployment/utils/zip_utils.py
gradient_adk/cli/config/agent_config_manager.py
gradient_adk/cli/config/yaml_agent_config_manager.py
gradient_adk/cli/templates/main.py.template
gradient_adk/digital_ocean_api/__init__.py
gradient_adk/digital_ocean_api/client_async.py
gradient_adk/digital_ocean_api/errors.py
gradient_adk/digital_ocean_api/models.py
gradient_adk/digital_ocean_api/utils/utils.py
gradient_adk/runtime/digitalocean_tracker.py
gradient_adk/runtime/helpers.py
gradient_adk/runtime/interfaces.py
gradient_adk/runtime/network_interceptor.py
gradient_adk/runtime/langgraph/__init__.py
gradient_adk/runtime/langgraph/langgraph_instrumentor.py
gradient_adk/runtime/pydanticai/__init__.py
gradient_adk/runtime/pydanticai/pydanticai_instrumentor.py
gradient_adk-0.2.10.dist-info/licenses/LICENSE
gradient_adk-0.2.10.dist-info/METADATA
gradient_adk-0.2.10.dist-info/WHEEL
gradient_adk-0.2.10.dist-info/entry_points.txt
gradient_adk-0.2.10.dist-info/top_level.txt
gradient_adk-0.2.10.dist-info/RECORD
