Metadata-Version: 2.4
Name: gradient-adk
Version: 0.2.10
Summary: Gradient AI Platform Agent Development Kit
License-Expression: Apache-2.0
Requires-Python: >=3.10
License-File: LICENSE
Requires-Dist: fastapi>=0.104.0
Requires-Dist: uvicorn[standard]>=0.24.0
Requires-Dist: pydantic>=2.5.0
Requires-Dist: typing-extensions>=4.8.0
Requires-Dist: typer>=0.12.0
Requires-Dist: PyYAML>=6.0
Requires-Dist: aiohttp>=3.8.0
Requires-Dist: pytest>=8.4.2
Requires-Dist: pytest-asyncio>=0.21.0
Requires-Dist: structlog>=24.1.0
Requires-Dist: pytest-cov>=7.0.0
Requires-Dist: httpx>=0.26.0
Requires-Dist: requests>=2.32.5
Requires-Dist: pytest-mock>=3.15.1
Requires-Dist: langgraph>=1.0.0
Requires-Dist: gradient>=3.10.1
Dynamic: license-file
